jupyter_process_manager/__init__.py
jupyter_process_manager/class_one_process.py
jupyter_process_manager/class_processes_manager.py
jupyter_process_manager/function_wrapper.py
jupyter_process_manager/gui/__init__.py
jupyter_process_manager/gui/layouts.py
jupyter_process_manager/gui/widget.py
jupyter_process_manager/logger.py
jupyter_process_manager-0.1.21.dist-info/LICENSE.txt
jupyter_process_manager-0.1.21.dist-info/WHEEL
jupyter_process_manager-0.1.21.dist-info/METADATA
jupyter_process_manager-0.1.21.dist-info/RECORD
