Metadata-Version: 2.1
Name: jupyter-process-manager
Version: 0.1.21
Summary: Python package with widget to simplify work with many processes in jupyter
Home-page: https://github.com/stas-prokopiev/jupyter_process_manager
License: MIT
Author: Stanislav Prokopyev
Author-email: stas.prokopiev@gmail.com
Requires-Python: >=3.7,<4.0
Classifier: License :: OSI Approved :: MIT License
Classifier: Programming Language :: Python :: 3
Classifier: Programming Language :: Python :: 3.10
Classifier: Programming Language :: Python :: 3.7
Classifier: Programming Language :: Python :: 3.8
Classifier: Programming Language :: Python :: 3.9
Requires-Dist: char (>=0.1.2,<0.2.0)
Requires-Dist: ipywidgets (>=7.7.0,<8.0.0)
Requires-Dist: ipywidgets-toggle-buttons (>=0.2.3,<0.3.0)
Requires-Dist: local-simple-database (>=0.1.10,<0.2.0)
Requires-Dist: nest-asyncio (>=1.5.5,<2.0.0)
Requires-Dist: psutil (>=5.9.0,<6.0.0)
Requires-Dist: round-to-n-significant-digits (>=0.1.5,<0.2.0)
Requires-Dist: tabulate (>=0.8.9,<0.9.0)
Requires-Dist: timedelta-nice-format (>=0.1.0,<0.2.0)
Requires-Dist: yaspin (>=2.1.0,<3.0.0)
Project-URL: Repository, https://github.com/stas-prokopiev/jupyter_process_manager
